strl/__init__.py
strl/strlclass.py
strl-1.2.dist-info/LICENSE.txt
strl-1.2.dist-info/METADATA
strl-1.2.dist-info/WHEEL
strl-1.2.dist-info/top_level.txt
strl-1.2.dist-info/RECORD
